seidr/__init__.py
seidr_data-0.1.0.dist-info/licenses/LICENSE
seidr_data-0.1.0.dist-info/METADATA
seidr_data-0.1.0.dist-info/WHEEL
seidr_data-0.1.0.dist-info/top_level.txt
seidr_data-0.1.0.dist-info/RECORD
