Metadata-Version: 2.4
Name: seidr-data
Version: 0.1.0
Summary: A petabyte scale data processing framework for AI models using Ray.
Author-email: Teraflop AI <enrico@teraflop.ai>
Classifier: Typing :: Typed
Classifier: Intended Audience :: Developers
Classifier: Programming Language :: Python :: 3.9
Classifier: Programming Language :: Python :: 3.10
Classifier: Programming Language :: Python :: 3.11
Classifier: Programming Language :: Python :: 3.12
Classifier: Programming Language :: Python :: 3.13
Classifier: Topic :: Software Development :: Libraries :: Python Modules
Requires-Python: >=3.9
License-File: LICENSE
Requires-Dist: ray[data]>=2.47.1
Requires-Dist: trafilatura>=2.0.0
Requires-Dist: warcio>=1.7.5
Dynamic: license-file
